{
  "kind": "youtube#videoListResponse",
  "etag": "3ga7xrGYfmnokFYuVbwpesK86DU",
  "items": [
    {
      "kind": "youtube#video",
      "etag": "qxRJTCaeIM_IfbkXevAtPZ46p2g",
      "id": "iYzZFernvh0",
      "snippet": {
        "publishedAt": "2024-04-18T15:15:01Z",
        "channelId": "UCIsEhwBMPkRHsEgqYAPQHsA",
        "title": "Candidates 2024 | Gukesh, Pragg, VD, Humpy, Vaishali | Rd 12 | Live: GM RB Ramesh, Amruta, Sagar",
        "description": "A Supergrandmaster's Guide to Openings by Anish Giri: https://chessbase.in/online-shop#!/A-Supergrandmasters-Guide-to-Openings-Vol-1-&-2-by-Anish-Giri-Pre-Order/p/647004877/category=0\n\nFIDE has launched their own shop celebrating 100 years of existence! Get your favourite products now - https://shop.fide.com/ - use coupon code CHESSBASE for 10% discount.\n\nChessBase 17 + Mega Database 2024 Combo - our bestseller: https://chessbase.in/online-shop#!/ChessBase-17-Mega-Database-2024-Combo/p/601221467\n\nGet the new ChessPa Activity Books: https://chessbase.in/online-shop#!/ChessPa-Activity-Books/p/603903576\n\nChessBase India Premium Chess set: https://chessbase.in/online-shop#!/ChessBase-India-Premium-Chess-Set/p/376637361\n\nIndian super GMs combo: https://chessbase.in/online-shop#!/Indian-Super-GM-combos/p/615237326\n\nJoin us live as chess history unfolds in Toronto, Canada! The 2024 Candidates Tournament brings together the world's top players, vying for a shot at the prestigious World Championship title. Witness intense battles and strategic masterpieces as these chess elite compete in a thrilling double round-robin format. Don't miss a moment of the action as the Great Hall becomes the battleground for this epic clash of minds. Tune in now and be part of the excitement!\n\nContribute here if you wish to help a chess player! https://helpchess.org/#believer \n\nPairings- Round 12:\n\nOpen\nHikaru Nakamura- Alireza Firouzja\nNijat Abasov - Gukesh D\nFabiano Caruana - Vidit Santosh Gujrathi\nIan Nepomniachtchi - Praggnanandhaa R\n\nWomen’s\nKateryna Lagno - Lei Tingjie\nAnna Muzychuk - Vaishali Rameshbabu\nAleksandra Goryachkina - Humpy Koneru\nNurgyul Salimova - Tan Zhongyi\n\nArticle: \nRound 1: https://chessbase.in/news/FIDE-Women-s-Candidates-2024-Round-1-report\n                https://chessbase.in/news/FIDE-Candidates-2024-Round-1-report\n\nRound 2: https://chessbase.in/news/FIDE-Candidates-2024-Round-2-report\n                 https://chessbase.in/news/FIDE-Women-s-Candidates-2024-Round-2-report\n\nRound 3: https://chessbase.in/news/FIDE-Candidates-2024-Round-3-report\n                 https://chessbase.in/news/FIDE-Women-s-Candidates-2024-Round-3-report\n\nRound 4: https://chessbase.in/news/FIDE-Candidates-2024-Round-4-report\n                 https://chessbase.in/news/FIDE-Women-s-Candidates-2024-Round-4-report\n\nRound 5: https://chessbase.in/news/FIDE-Candidates-2024-Round-5-report\n                 https://chessbase.in/news/FIDE-Women-s-Candidates-2024-Round-5-report\n\nRound 6: https://chessbase.in/news/FIDE-Candidates-2024-Round-6-report\n                 https://chessbase.in/news/FIDE-Women-s-Candidates-2024-Round-6-report\n\nRound 7: https://chessbase.in/news/FIDE-Candidates-2024-Round-7-report\n                 https://chessbase.in/news/FIDE-Women-s-Candidates-2024-Round-7-report\n\nRound 8: https://chessbase.in/news/FIDE-Candidates-2024-Round-8-report\n                 https://chessbase.in/news/FIDE-Women-s-Candidates-2024-Round-8-report\n\nRound 9: https://chessbase.in/news/FIDE-Candidates-2024-Round-9-report\n                 https://chessbase.in/news/FIDE-Women-s-Candidates-2024-Round-9-report\n\nRound 10: https://chessbase.in/news/FIDE-Candidates-2024-Round-10-report\n                 https://chessbase.in/news/FIDE-Women-s-Candidates-2024-Round-10-report\n\nRound 11: https://chessbase.in/news/FIDE-Candidates-2024-Round-11-report\n                 https://chessbase.in/news/FIDE-Women-s-Candidates-2024-Round-11-report\n\nVideo:  ChessBase India\n\n#Chess #ChessBaseIndia #candidates2024 #praggnanandhaa #gukesh #viditgujrathi #vaishali #humpy #hikarunakamura \n----------------------------------------------------------------\n◾ChessBase India channel: https://www.youtube.com/c/ChessBaseIndiachannel\n◾Support young talents via HelpChess Foundation: https://helpchess.org/\n◾Review us on Google: https://g.page/r/CZ5T1PaLM-7WEBE/review\n◾Website: http://chessbase.in\n◾ChessBase India Clips: https://www.youtube.com/channel/UCjYrfY1-CCX2pagdnRrNUpA\n◾ChessBase India Hindi: https://www.youtube.com/c/ChessBaseIndiaHindi\n◾Chess Shop: https://chessbase.in/online-shop/\n◾Chess Calendar: https://chessbase.in/calendar\n◾ChessBase India on amazon: https://amzn.to/2vv0XXy\n◾Twitter: https://twitter.com/ChessbaseIndia\n◾Facebook: https://www.facebook.com/chessbaseindia/\n◾Instagram: https://www.instagram.com/chessbaseindia \n◾Contact us: chessbaseindia@gmail.com",
        "thumbnails": {
          "default": {
            "url": "https://i.ytimg.com/vi/iYzZFernvh0/default_live.jpg",
            "width": 120,
            "height": 90
          },
          "medium": {
            "url": "https://i.ytimg.com/vi/iYzZFernvh0/mqdefault_live.jpg",
            "width": 320,
            "height": 180
          },
          "high": {
            "url": "https://i.ytimg.com/vi/iYzZFernvh0/hqdefault_live.jpg",
            "width": 480,
            "height": 360
          },
          "standard": {
            "url": "https://i.ytimg.com/vi/iYzZFernvh0/sddefault_live.jpg",
            "width": 640,
            "height": 480
          },
          "maxres": {
            "url": "https://i.ytimg.com/vi/iYzZFernvh0/maxresdefault_live.jpg",
            "width": 1280,
            "height": 720
          }
        },
        "channelTitle": "ChessBase India",
        "tags": [
          "chessbaseindia",
          "interviews",
          "chesstraining",
          "improvechess",
          "chess",
          "how to play chess"
        ],
        "categoryId": "17",
        "liveBroadcastContent": "live",
        "localized": {
          "title": "Candidates 2024 | Gukesh, Pragg, VD, Humpy, Vaishali | Rd 12 | Live: GM RB Ramesh, Amruta, Sagar",
          "description": "A Supergrandmaster's Guide to Openings by Anish Giri: https://chessbase.in/online-shop#!/A-Supergrandmasters-Guide-to-Openings-Vol-1-&-2-by-Anish-Giri-Pre-Order/p/647004877/category=0\n\nFIDE has launched their own shop celebrating 100 years of existence! Get your favourite products now - https://shop.fide.com/ - use coupon code CHESSBASE for 10% discount.\n\nChessBase 17 + Mega Database 2024 Combo - our bestseller: https://chessbase.in/online-shop#!/ChessBase-17-Mega-Database-2024-Combo/p/601221467\n\nGet the new ChessPa Activity Books: https://chessbase.in/online-shop#!/ChessPa-Activity-Books/p/603903576\n\nChessBase India Premium Chess set: https://chessbase.in/online-shop#!/ChessBase-India-Premium-Chess-Set/p/376637361\n\nIndian super GMs combo: https://chessbase.in/online-shop#!/Indian-Super-GM-combos/p/615237326\n\nJoin us live as chess history unfolds in Toronto, Canada! The 2024 Candidates Tournament brings together the world's top players, vying for a shot at the prestigious World Championship title. Witness intense battles and strategic masterpieces as these chess elite compete in a thrilling double round-robin format. Don't miss a moment of the action as the Great Hall becomes the battleground for this epic clash of minds. Tune in now and be part of the excitement!\n\nContribute here if you wish to help a chess player! https://helpchess.org/#believer \n\nPairings- Round 12:\n\nOpen\nHikaru Nakamura- Alireza Firouzja\nNijat Abasov - Gukesh D\nFabiano Caruana - Vidit Santosh Gujrathi\nIan Nepomniachtchi - Praggnanandhaa R\n\nWomen’s\nKateryna Lagno - Lei Tingjie\nAnna Muzychuk - Vaishali Rameshbabu\nAleksandra Goryachkina - Humpy Koneru\nNurgyul Salimova - Tan Zhongyi\n\nArticle: \nRound 1: https://chessbase.in/news/FIDE-Women-s-Candidates-2024-Round-1-report\n                https://chessbase.in/news/FIDE-Candidates-2024-Round-1-report\n\nRound 2: https://chessbase.in/news/FIDE-Candidates-2024-Round-2-report\n                 https://chessbase.in/news/FIDE-Women-s-Candidates-2024-Round-2-report\n\nRound 3: https://chessbase.in/news/FIDE-Candidates-2024-Round-3-report\n                 https://chessbase.in/news/FIDE-Women-s-Candidates-2024-Round-3-report\n\nRound 4: https://chessbase.in/news/FIDE-Candidates-2024-Round-4-report\n                 https://chessbase.in/news/FIDE-Women-s-Candidates-2024-Round-4-report\n\nRound 5: https://chessbase.in/news/FIDE-Candidates-2024-Round-5-report\n                 https://chessbase.in/news/FIDE-Women-s-Candidates-2024-Round-5-report\n\nRound 6: https://chessbase.in/news/FIDE-Candidates-2024-Round-6-report\n                 https://chessbase.in/news/FIDE-Women-s-Candidates-2024-Round-6-report\n\nRound 7: https://chessbase.in/news/FIDE-Candidates-2024-Round-7-report\n                 https://chessbase.in/news/FIDE-Women-s-Candidates-2024-Round-7-report\n\nRound 8: https://chessbase.in/news/FIDE-Candidates-2024-Round-8-report\n                 https://chessbase.in/news/FIDE-Women-s-Candidates-2024-Round-8-report\n\nRound 9: https://chessbase.in/news/FIDE-Candidates-2024-Round-9-report\n                 https://chessbase.in/news/FIDE-Women-s-Candidates-2024-Round-9-report\n\nRound 10: https://chessbase.in/news/FIDE-Candidates-2024-Round-10-report\n                 https://chessbase.in/news/FIDE-Women-s-Candidates-2024-Round-10-report\n\nRound 11: https://chessbase.in/news/FIDE-Candidates-2024-Round-11-report\n                 https://chessbase.in/news/FIDE-Women-s-Candidates-2024-Round-11-report\n\nVideo:  ChessBase India\n\n#Chess #ChessBaseIndia #candidates2024 #praggnanandhaa #gukesh #viditgujrathi #vaishali #humpy #hikarunakamura \n----------------------------------------------------------------\n◾ChessBase India channel: https://www.youtube.com/c/ChessBaseIndiachannel\n◾Support young talents via HelpChess Foundation: https://helpchess.org/\n◾Review us on Google: https://g.page/r/CZ5T1PaLM-7WEBE/review\n◾Website: http://chessbase.in\n◾ChessBase India Clips: https://www.youtube.com/channel/UCjYrfY1-CCX2pagdnRrNUpA\n◾ChessBase India Hindi: https://www.youtube.com/c/ChessBaseIndiaHindi\n◾Chess Shop: https://chessbase.in/online-shop/\n◾Chess Calendar: https://chessbase.in/calendar\n◾ChessBase India on amazon: https://amzn.to/2vv0XXy\n◾Twitter: https://twitter.com/ChessbaseIndia\n◾Facebook: https://www.facebook.com/chessbaseindia/\n◾Instagram: https://www.instagram.com/chessbaseindia \n◾Contact us: chessbaseindia@gmail.com"
        },
        "defaultAudioLanguage": "en-IN"
      },
      "statistics": {
        "viewCount": "983",
        "likeCount": "1252",
        "favoriteCount": "0",
        "commentCount": "0"
      },
      "liveStreamingDetails": {
        "actualStartTime": "2024-04-18T18:28:32Z",
        "scheduledStartTime": "2024-04-18T18:25:00Z",
        "concurrentViewers": "3670",
        "activeLiveChatId": "Cg0KC2lZelpGZXJudmgwKicKGFVDSXNFaHdCTVBrUkhzRWdxWUFQUUhzQRILaVl6WkZlcm52aDA"
      }
    }
  ],
  "pageInfo": { "totalResults": 1, "resultsPerPage": 1 }
}
